mu0_reg12.v
// MU0 12 bit register design - behavioural style
// P W Nutter (based on a design by Jeff Pepper)
// Date 20/8/2021
// 

// Do not touch the following line it is required for simulation 
`timescale 1ns/100ps

// for simulation purposes, do not delete
`default_nettype none

// module header

module mu0_reg12(input  wire        Clk, 
	            input  wire        Reset,     
			  input  wire        En, 
			  input  wire [11:0] D, 
			  output reg  [11:0] Q);

// behavioural code - clock driven

always @ (posedge Clk, posedge Reset)
begin
     case(Reset)
		1'b1: Q <= 12'h000; //if reset high, clear reg
		1'b0: if (En)
			 	Q <= D;
		      else Q <= Q;
		default: Q <= 12'h000;	
     endcase	
end
endmodule 

// for simulation purposes, do not delete
`default_nettype wire

mu0_reg12_tb.v
// MU0 12 bit register testbench
// P W Nutter (based on a design by Jeff Pepper)
// Date 20/8/2021
// 

// Do not touch the following line it is required for simulation 
`timescale 1ns/100ps 

// module header

module mu0_reg12_tb();

// Define any internal connections

reg Clk;
reg Reset;
reg En;
reg[11:0] D;
wire[11:0] Q;



// Instantiate mu0_reg12 as dut (device under test)
mu0_reg12 dut(Clk, Reset, En, D, Q);

// Set up the clock

// the following initial block initialises the clock

initial Clk = 0;

// the following always block creates the clock signal

always 
 begin
    #50
    Clk = ~Clk;     // Inverts the Clock
 end


// Test vectors
initial
begin 
	#0 Reset = 1'b1; En = 1'b1; D = 12'hFFE; 			// Reset goes high and D is not loaded in reg even when En is high 
	#200 Reset = 1'b0;  
	#200 Reset = 1'b0; En = 1'b0; D = 12'hFFA; 		// Enable goes Low, the new value of D is not loaded
	#200 Reset = 1'b0; En = 1'b1;  
	#275 Reset = 1'b1;  										// Testing asynchronous behaviour of Reset
	#125 Reset = 1'b0; 										// Loading the data back in reg
	#200 En = 1'b0;
	#200 Reset = 1'b1; 										// When En == 0, Data is still overwritten by the Reset
   #100 $finish;      										// End the simulation
end
 
// Save results as VCD file 
// Do not change
initial
 begin
  $dumpfile("mu0_reg12_tb_results.vcd");  // Save simulation waveforms in this file
  $dumpvars; // Capture all simulation waveforms
 end

endmodule

mu0_reg12_tb_results.vcd
$date
	Mon Dec  6 10:00:16 2021
$end
$version
	Icarus Verilog
$end
$timescale
	100ps
$end
$scope module mu0_reg12_tb $end
$var wire 12 ! Q [11:0] $end
$var reg 1 " Clk $end
$var reg 12 # D [11:0] $end
$var reg 1 $ En $end
$var reg 1 % Reset $end
$scope module dut $end
$var wire 1 " Clk $end
$var wire 12 & D [11:0] $end
$var wire 1 $ En $end
$var wire 1 % Reset $end
$var reg 12 ' Q [11:0] $end
$upscope $end
$upscope $end
$enddefinitions $end
#0
$dumpvars
b0 '
b111111111110 &
1%
1$
b111111111110 #
0"
b0 !
$end
#500
1"
#1000
0"
#1500
1"
#2000
0"
0%
#2500
b111111111110 !
b111111111110 '
1"
#3000
0"
#3500
1"
#4000
0"
b111111111010 #
b111111111010 &
0$
#4500
1"
#5000
0"
#5500
1"
#6000
0"
1$
#6500
b111111111010 !
b111111111010 '
1"
#7000
0"
#7500
1"
#8000
0"
#8500
1"
#8750
b0 !
b0 '
1%
#9000
0"
#9500
1"
#10000
0"
0%
#10500
b111111111010 !
b111111111010 '
1"
#11000
0"
#11500
1"
#12000
0"
0$
#12500
1"
#13000
0"
#13500
1"
#14000
b0 !
b0 '
0"
1%
